n2w_it/__init__.py
n2w_it/__main__.py
n2w_it/n2w_it.py
n2w_it-1.0.1.dist-info/LICENSE.md
n2w_it-1.0.1.dist-info/METADATA
n2w_it-1.0.1.dist-info/WHEEL
n2w_it-1.0.1.dist-info/entry_points.txt
n2w_it-1.0.1.dist-info/top_level.txt
n2w_it-1.0.1.dist-info/RECORD
